llama_index/utils/huggingface/__init__.py
llama_index/utils/huggingface/base.py
llama_index_utils_huggingface-0.4.1.dist-info/METADATA
llama_index_utils_huggingface-0.4.1.dist-info/WHEEL
llama_index_utils_huggingface-0.4.1.dist-info/licenses/LICENSE
llama_index_utils_huggingface-0.4.1.dist-info/RECORD
