Metadata-Version: 2.4
Name: llama-index-utils-huggingface
Version: 0.4.1
Summary: llama-index utils for huggingface integration
Author-email: Your Name <you@example.com>
License-Expression: MIT
License-File: LICENSE
Requires-Python: <4.0,>=3.9
Requires-Dist: huggingface-hub[inference]>=0.19.0
Requires-Dist: llama-index-core<0.15,>=0.13.0
